wumpus/__init__.py
wumpus-0.0.1.dist-info/METADATA
wumpus-0.0.1.dist-info/WHEEL
wumpus-0.0.1.dist-info/top_level.txt
wumpus-0.0.1.dist-info/RECORD
